ntp.py
python_ntp-1.0.0.dist-info/LICENSE.txt
python_ntp-1.0.0.dist-info/METADATA
python_ntp-1.0.0.dist-info/WHEEL
python_ntp-1.0.0.dist-info/entry_points.txt
python_ntp-1.0.0.dist-info/top_level.txt
python_ntp-1.0.0.dist-info/zip-safe
python_ntp-1.0.0.dist-info/RECORD
