Metadata-Version: 2.1
Name: python-ntp
Version: 1.0.0
Summary: UNKNOWN
Home-page: https://github.com/jsiembida/python-ntp
Author: Jarek Siembida
Author-email: jarek.siembida@gmail.com
License: ASF2.0
Platform: UNKNOWN
Classifier: Intended Audience :: Developers
Classifier: Intended Audience :: Information Technology
Classifier: Intended Audience :: System Administrators
Classifier: License :: OSI Approved :: Apache Software License
Classifier: Operating System :: MacOS :: MacOS X
Classifier: Operating System :: Microsoft :: Windows
Classifier: Operating System :: POSIX :: BSD
Classifier: Operating System :: POSIX :: Linux
Classifier: Operating System :: Unix
Classifier: Programming Language :: Python :: 3
Classifier: Topic :: Software Development :: Libraries :: Python Modules
Classifier: Topic :: System :: Networking :: Time Synchronization
Classifier: Topic :: Utilities
Requires-Python: >=3.5
